little_conf/__init__.py
little_conf/lc.py
little_conf/template_settings/__init__.py
little_conf/template_settings/base.py
little_conf/template_settings/database.py
little_conf/template_settings/redis.py
little_conf/template_settings/s3.py
little_conf-0.0.4.dist-info/WHEEL
little_conf-0.0.4.dist-info/METADATA
little_conf-0.0.4.dist-info/RECORD
