Metadata-Version: 2.1
Name: little-conf
Version: 0.0.4
Summary: Simple library for service configuration
Home-page: https://github.com/smartleks/little-conf
Author: smartleks
Requires-Python: >=3.7,<4.0
Classifier: Programming Language :: Python :: 3
Classifier: Programming Language :: Python :: 3.7
Classifier: Programming Language :: Python :: 3.8
Classifier: Programming Language :: Python :: 3.9
Classifier: Programming Language :: Python :: 3.10
Classifier: Programming Language :: Python :: 3.11
Requires-Dist: deepmerge (>=1.1.0,<2.0.0)
Requires-Dist: pydantic (>=1.8.0,<2.0.0)
Requires-Dist: pytest (>=6.2.4,<7.0.0)
Requires-Dist: pyyaml (>5.0.0)
Project-URL: Repository, https://github.com/smartleks/little-conf
